Metadata-Version: 1.0
Name: micral-utils
Version: 2.0
Summary: Utilities for Micral packages
Home-page: UNKNOWN
Author: Yann LEROY
Author-email: yann.leroy102@orange.fr
License: MIT
Platform: UNKNOWN
